pywebio3/__init__.py
pywebio3/__version__.py
pywebio3/exceptions.py
pywebio3/html/codemirror/active-line.js
pywebio3/html/codemirror/addons.js
pywebio3/html/codemirror/autorefresh.js
pywebio3/html/codemirror/loadmode.js
pywebio3/html/codemirror/matchbrackets.js
pywebio3/html/codemirror/python.js
pywebio3/html/css/app.css
pywebio3/html/css/bootstrap-select.min.css
pywebio3/html/css/bs-theme/dark.min.css
pywebio3/html/css/bs-theme/default.min.css
pywebio3/html/css/bs-theme/minty.min.css
pywebio3/html/css/bs-theme/sketchy.min.css
pywebio3/html/css/bs-theme/yeti.min.css
pywebio3/html/css/codemirror.min.css
pywebio3/html/css/markdown.min.css
pywebio3/html/css/toastify.min.css
pywebio3/html/image/apple-touch-icon.png
pywebio3/html/image/favicon_closed_16.png
pywebio3/html/image/favicon_closed_32.png
pywebio3/html/image/favicon_open_16.png
pywebio3/html/image/favicon_open_32.png
pywebio3/html/js/bootstrap-select.min.js
pywebio3/html/js/bootstrap.min.js
pywebio3/html/js/bs-custom-file-input.min.js
pywebio3/html/js/codemirror.min.js
pywebio3/html/js/FileSaver.min.js
pywebio3/html/js/jquery.min.js
pywebio3/html/js/mustache.min.js
pywebio3/html/js/popper.min.js
pywebio3/html/js/prism.min.js
pywebio3/html/js/purify.min.js
pywebio3/html/js/pywebio3.min.js
pywebio3/html/js/require.min.js
pywebio3/html/js/toastify.min.js
pywebio3/input.py
pywebio3/io_ctrl.py
pywebio3/output.py
pywebio3/pin.py
pywebio3/platform/__init__.py
pywebio3/platform/adaptor/__init__.py
pywebio3/platform/adaptor/http.py
pywebio3/platform/adaptor/ws.py
pywebio3/platform/aiohttp.py
pywebio3/platform/bokeh.py
pywebio3/platform/django.py
pywebio3/platform/fastapi.py
pywebio3/platform/flask.py
pywebio3/platform/page.py
pywebio3/platform/path_deploy.py
pywebio3/platform/pyinstaller/__init__.py
pywebio3/platform/pyinstaller/hook-pywebio.py
pywebio3/platform/remote_access.py
pywebio3/platform/tornado.py
pywebio3/platform/tornado_http.py
pywebio3/platform/tpl/index.html
pywebio3/platform/utils.py
pywebio3-0.1.2.dist-info/LICENSE
pywebio3-0.1.2.dist-info/METADATA
pywebio3-0.1.2.dist-info/WHEEL
pywebio3-0.1.2.dist-info/RECORD
